{
  "profiles": [
    {
      "name": "A319 Headwind",
      "matches": ["A319", "Headwind", "ACJ319", "Airbus A319", "A319_FENIX", "A319 FENIX", "A319-1"],
      "exact_titles": ["Private ACJ319 CFM", "A319 Fenix", "Fenix A319"],
      "description": "Airbus A319 by Headwind Simulations",
      "fuel": {
        "primary": "FUEL TOTAL QUANTITY WEIGHT",
        "fallbacks": ["FUEL LEFT QUANTITY", "FUEL RIGHT QUANTITY", "FUEL CENTER QUANTITY", "FUEL TOTAL CAPACITY"],
        "unit": "pounds",
        "status": "WORKING"
      },
      "engines": {
        "n1_variable": "TURB ENG N1",
        "fuel_flow_variable": "GENERAL ENG FUEL FLOW PPH",
        "status": "LVAR_REQUIRED",
        "lvars": ["A319_Engine_N1_1", "A319_Engine_N1_2"]
      },
      "lights": {
        "status": "LVAR_REQUIRED",
        "lvars": ["A319_Light_Beacon", "A319_Light_Strobe", "A319_Light_Landing", "A319_Light_Nav", "A319_Light_Taxi"],
        "notes": "SimConnect returns 0, real state in WASM LVARs"
      },
      "squawk": {
        "format": "BCO16",
        "status": "LVAR_REQUIRED",
        "lvar": "A319_Transponder_Code",
        "notes": "SimConnect value is unreliable"
      },
      "cabin": {
        "status": "LVAR_REQUIRED",
        "altitude_lvar": "A319_Cabin_Altitude",
        "pressure_lvar": "A319_Cabin_Pressure",
        "notes": "SimConnect returns garbage values"
      },
      "supported": true,
      "recommended_backend": "SimConnect",
      "lvar_support": "REQUIRED_FOR_FULL_FUNCTIONALITY",
      "working_with_simconnect": ["Position", "Altitude", "Fuel", "Heading", "Speed", "Flaps", "Gear"],
      "requires_lvars": ["Lights", "Engine N1", "Transponder", "Cabin Pressure"],
      "notes": "Uses WASM extensively. Basic flight data works via SimConnect, detailed systems require LVARs"
    },
    {
      "name": "Fenix A320",
      "matches": ["A320", "Fenix", "Airbus A320"],
      "description": "Airbus A320 by Fenix Simulations",
      "fuel": {
        "primary": "FUEL TOTAL QUANTITY WEIGHT",
        "fallbacks": ["FUEL LEFT QUANTITY", "FUEL RIGHT QUANTITY", "FUEL CENTER QUANTITY"],
        "unit": "pounds"
      },
      "engines": {
        "n1_variable": "TURB ENG N1",
        "fuel_flow_variable": "GENERAL ENG FUEL FLOW PPH"
      },
      "lights": {
        "use_native": true
      },
      "squawk": {
        "format": "BCO16"
      },
      "supported": true,
      "recommended_backend": "SimConnect",
      "notes": "Complex WASM systems"
    },
    {
      "name": "Headwind A320",
      "matches": ["A320N", "A20N", "Headwind A320", "A320 Headwind", "Airbus A320-251"],
      "exact_titles": [],
      "description": "Airbus A320neo by Headwind Simulations",
      "fuel": {
        "primary": "FUEL TOTAL QUANTITY WEIGHT",
        "fallbacks": ["FUEL LEFT QUANTITY", "FUEL RIGHT QUANTITY", "FUEL CENTER QUANTITY"],
        "unit": "pounds",
        "status": "WORKING"
      },
      "engines": {
        "n1_variable": "TURB ENG N1",
        "status": "LVAR_REQUIRED",
        "lvars": ["A32NX_ENGINE_N1:1", "A32NX_ENGINE_N1:2"]
      },
      "lights": {
        "status": "LVAR_REQUIRED",
        "notes": "Same LVARs as FBW A32NX"
      },
      "supported": true,
      "recommended_backend": "SimConnect",
      "lvar_support": "REQUIRED_FOR_FULL_FUNCTIONALITY",
      "working_with_simconnect": ["Position", "Altitude", "Fuel", "Heading", "Speed", "Flaps", "Gear"],
      "requires_lvars": ["Lights", "Engine N1", "Transponder"],
      "notes": "Uses A32NX LVAR namespace"
    },
    {
      "name": "FlyByWire A32NX",
      "matches": ["A32NX", "Flybywire", "FlyByWire", "FBW", "FBW A320", "FlyByWire A32NX"],
      "description": "FlyByWire A32NX Airbus family",
      "fuel": {
        "primary": "FUEL TOTAL QUANTITY WEIGHT",
        "fallbacks": ["FUEL LEFT QUANTITY", "FUEL RIGHT QUANTITY", "FUEL TOTAL CAPACITY"],
        "unit": "pounds",
        "status": "WORKING"
      },
      "engines": {
        "n1_variable": "(L:A32NX_ENGINE_N1:1, percent)",
        "status": "LVAR_REQUIRED",
        "lvars": ["(L:A32NX_ENGINE_N1:1, percent)", "(L:A32NX_ENGINE_N1:2, percent)"]
      },
      "lights": {
        "status": "LVAR_REQUIRED",
        "notes": "Usa LVARs A32NX para todas las luces principales"
      },
      "supported": true,
      "recommended_backend": "SimConnect",
      "lvar_support": "REQUIRED_FOR_FULL_FUNCTIONALITY",
      "working_with_simconnect": ["Position", "Altitude", "Fuel", "Heading", "Speed", "Flaps", "Gear"],
      "requires_lvars": ["Lights", "Engine N1"],
      "notes": "FlyByWire A32NX usa sus propios LVARs compatibles con la integración"
    },
    {
      "name": "PMDG 737",
      "matches": ["B737", "PMDG 737", "Boeing 737", "737-800", "737-700", "737-900", "737 MAX"],
      "description": "Boeing 737 series by PMDG",
      "fuel": {
        "primary": "FUEL TOTAL QUANTITY WEIGHT",
        "unit": "pounds"
      },
      "engines": {
        "n1_variable": "TURB ENG N1",
        "fuel_flow_variable": "GENERAL ENG FUEL FLOW PPH"
      },
      "supported": true,
      "recommended_backend": "SimConnect",
      "notes": "PMDG SDK required for full functionality"
    },
    {
      "name": "PMDG 777",
      "matches": ["B777", "B77W", "PMDG 777"],
      "description": "Boeing 777 by PMDG",
      "fuel": {
        "primary": "FUEL TOTAL QUANTITY WEIGHT",
        "unit": "pounds"
      },
      "engines": {
        "n1_variable": "TURB ENG N1",
        "fuel_flow_variable": "GENERAL ENG FUEL FLOW PPH"
      },
      "supported": true,
      "recommended_backend": "SimConnect",
      "notes": "PMDG SDK recommended"
    },
    {
      "name": "BlackSquare TBM8",
      "matches": ["TBM8", "BlackSquare"],
      "description": "TBM 850 by BlackSquare",
      "fuel": {
        "primary": "FUEL TOTAL QUANTITY WEIGHT",
        "unit": "pounds"
      },
      "engines": {
        "n1_variable": "ENG N1 RPM",
        "fuel_flow_variable": "GENERAL ENG FUEL FLOW PPH"
      },
      "supported": true,
      "recommended_backend": "SimConnect",
      "notes": "High-fidelity turboprop"
    },
    {
      "name": "MSFS Native",
      "matches": ["*"],
      "description": "Default profile for standard MSFS aircraft",
      "fuel": {
        "primary": "FUEL TOTAL QUANTITY WEIGHT",
        "unit": "pounds"
      },
      "engines": {
        "n1_variable": "ENG N1 RPM",
        "fuel_flow_variable": "GENERAL ENG FUEL FLOW PPH"
      },
      "supported": true,
      "recommended_backend": "FSUIPC7",
      "notes": "Standard aircraft work with both backends"
    }
  ],
  "config": {
    "auto_detect": true,
    "fallback_to_simconnect": true,
    "log_profile_selection": true,
    "validate_data_ranges": true
  }
}
