{
  "version": "3.2.1",
  "webVersion": "2.0",
  "downloadUrl": "https://qoradagitvccyabfkgkw.supabase.co/storage/v1/object/public/acars-releases/PatagoniaWingsACARSSetup-3.2.1.exe",
  "mandatory": false,
  "notes": "- Matriz de reglaje final Patagonia Wings aplicada al nucleo de evaluacion\n- Tabla de aterrizaje oficial: 0/-59 demasiado suave, -60/-180 perfecto, -181/-250 bueno, -251/-500 duro, -501/-700 mantenimiento, <-701 accidentado\n- Sistemas de cabina solo penalizan si el perfil del avion los lee de forma confiable (cabinSystemsReliable)\n- Transponder: informativo, no penalizacion dura (P3)\n- Reglas de emergencias / abortos / crash consolidadas\n- Contrato unico Supabase/Web/ACARS sin duplicidades",
  "releaseDate": "2026-04-18",
  "minVersion": "2.0.5",
  "fileSize": "22.6 MB",
  "storageProvider": "supabase"
}
